zlai/__init__.py
zlai/agent/__init__.py
zlai/agent/address.py
zlai/agent/base.py
zlai/agent/chat.py
zlai/agent/config.py
zlai/agent/csv.py
zlai/agent/fund.py
zlai/agent/graph/__init__.py
zlai/agent/graph/graph.py
zlai/agent/knowledge.py
zlai/agent/long_write/__init__.py
zlai/agent/long_write/long_write.py
zlai/agent/parse.py
zlai/agent/pre_version/__init__.py
zlai/agent/pre_version/temp.py
zlai/agent/prompt/__init__.py
zlai/agent/prompt/address.py
zlai/agent/prompt/auto_web.py
zlai/agent/prompt/bing.py
zlai/agent/prompt/chat.py
zlai/agent/prompt/csv.py
zlai/agent/prompt/fund.py
zlai/agent/prompt/knowledge.py
zlai/agent/prompt/long_write.py
zlai/agent/prompt/pyecharts.py
zlai/agent/prompt/shell.py
zlai/agent/prompt/sqlite.py
zlai/agent/prompt/tasks.py
zlai/agent/prompt/weather.py
zlai/agent/shell.py
zlai/agent/sqlite.py
zlai/agent/task_description.py
zlai/agent/tasks.py
zlai/agent/tools/__init__.py
zlai/agent/tools/register.py
zlai/agent/tools/schema.py
zlai/agent/tools/tools.py
zlai/agent/tools/tools_agent.py
zlai/agent/try_times.py
zlai/agent/weather.py
zlai/agent/web/__init__.py
zlai/agent/web/auto_web_selenium.py
zlai/agent/web/auto_web_unstructured.py
zlai/agent/web/bing.py
zlai/agent/web/links.py
zlai/agent/web/web_search.py
zlai/database/__init__.py
zlai/database/spark.py
zlai/database/sql.py
zlai/documents/__init__.py
zlai/documents/load.py
zlai/documents/load_md.py
zlai/documents/pdf.py
zlai/documents/read.py
zlai/documents/save.py
zlai/elasticsearch/__init__.py
zlai/elasticsearch/config.py
zlai/elasticsearch/document.py
zlai/elasticsearch/elasticsearch.py
zlai/embedding/__init__.py
zlai/embedding/ali.py
zlai/embedding/emb_utils.py
zlai/embedding/embedding.py
zlai/embedding/embedding_config/__init__.py
zlai/embedding/embedding_config/ali.py
zlai/embedding/embedding_config/base.py
zlai/embedding/embedding_config/openai.py
zlai/embedding/embedding_config/zhipu.py
zlai/embedding/openai.py
zlai/embedding/pretrained.py
zlai/embedding/schema.py
zlai-0.3.116.dist-info/LICENSE
zlai-0.3.116.dist-info/METADATA
zlai-0.3.116.dist-info/WHEEL
zlai-0.3.116.dist-info/entry_points.txt
zlai-0.3.116.dist-info/RECORD
