Metadata-Version: 2.1
Name: zlai
Version: 0.3.116
Summary: A LLM Agent Python package.
Home-page: https://zlai-llm.github.io/zlai-doc/#/
License: MIT
Keywords: llm,agent,embedding,chatbot,prompt
Author: chensy cao
Author-email: chensy.cao@foxmail.com
Requires-Python: >=3.9, !=2.7.*, !=3.0.*, !=3.1.*, !=3.2.*, !=3.3.*, !=3.4.*, !=3.5.*, !=3.6.*, !=3.7.*, !=3.8.*
Classifier: License :: OSI Approved :: MIT License
Classifier: Operating System :: OS Independent
Classifier: Programming Language :: Python :: 3
Classifier: Programming Language :: Python :: 3.9
Classifier: Programming Language :: Python :: 3.10
Classifier: Programming Language :: Python :: 3.11
Classifier: Programming Language :: Python :: 3.12
Classifier: Topic :: Software Development :: Libraries
Classifier: Topic :: Software Development :: Libraries :: Python Modules
Provides-Extra: all
Provides-Extra: api
Provides-Extra: database
Provides-Extra: echarts
Provides-Extra: langchain
Provides-Extra: local
Provides-Extra: streamlit
Provides-Extra: tiny
Provides-Extra: unstructured
Provides-Extra: vector-db
Provides-Extra: web
Requires-Dist: accelerate (>=0.33.0,<0.34.0) ; extra == "all" or extra == "local"
Requires-Dist: bs4 (>=0.0.2,<0.0.3) ; extra == "all" or extra == "streamlit"
Requires-Dist: cachetools (>=5.4.0,<6.0.0)
Requires-Dist: chardet (>=5.2.0,<6.0.0)
Requires-Dist: click (>=8.1.7,<9.0.0) ; extra == "all" or extra == "local"
Requires-Dist: colorama (>=0.4.6)
Requires-Dist: dashscope (>=1.14.1) ; extra == "all" or extra == "api"
Requires-Dist: diffusers (==0.30.0) ; extra == "all" or extra == "local"
Requires-Dist: elasticsearch (>=8.14.0,<9.0.0) ; extra == "all" or extra == "vector-db"
Requires-Dist: elasticsearch-dsl (>=8.14.0,<9.0.0) ; extra == "all" or extra == "vector-db"
Requires-Dist: fastapi (>=0.111.1,<0.112.0) ; extra == "all" or extra == "local"
Requires-Dist: httpx (>=0.24.1) ; extra == "all" or extra == "web"
Requires-Dist: langchain-core (>=0.2.11,<0.3.0) ; extra == "all" or extra == "langchain"
Requires-Dist: langchain-experimental (>=0.0.62,<0.0.63) ; extra == "all" or extra == "langchain"
Requires-Dist: lxml (>=5.3.0,<6.0.0)
Requires-Dist: numpy (>=1.23.5)
Requires-Dist: openai (>=1.26.0) ; extra == "all" or extra == "tiny" or extra == "api"
Requires-Dist: pandas (>=1.0)
Requires-Dist: pydantic (>=2.8.2,<3.0.0)
Requires-Dist: pyecharts (>=2.0.5) ; extra == "all" or extra == "echarts"
Requires-Dist: pymilvus (>=2.4.1) ; extra == "all" or extra == "vector-db"
Requires-Dist: pyspark (>=3.5.1,<4.0.0) ; extra == "all" or extra == "database"
Requires-Dist: qianfan (>=0.3.18) ; extra == "all" or extra == "api"
Requires-Dist: requests (>=2.32.3,<3.0.0)
Requires-Dist: selenium (>=4.19.0) ; extra == "all" or extra == "web"
Requires-Dist: sentence-transformers (>=3.0.1,<4.0.0) ; extra == "all" or extra == "local"
Requires-Dist: sqlalchemy (>=2.0.20) ; extra == "all" or extra == "database"
Requires-Dist: streamlit (>=1.36.0,<2.0.0) ; extra == "all" or extra == "streamlit"
Requires-Dist: tabulate (>=0.9.0,<0.10.0)
Requires-Dist: tencentcloud-sdk-python (>=3.0.1182,<4.0.0) ; extra == "all" or extra == "api"
Requires-Dist: termcolor (>=2.3.0)
Requires-Dist: torch (>=2.1.0) ; extra == "all" or extra == "local"
Requires-Dist: tqdm (>=4.65.0)
Requires-Dist: transformers (>=4.43.3,<5.0.0) ; extra == "all" or extra == "local"
Requires-Dist: unstructured[pdf] (>=0.10.5) ; extra == "all" or extra == "unstructured"
Requires-Dist: uvicorn (>=0.30.3,<0.31.0) ; extra == "all" or extra == "local"
Requires-Dist: zhipuai (>=2.0.1) ; extra == "all" or extra == "tiny" or extra == "api"
Project-URL: Bug Tracker, https://github.com/zlai-llm/zlai/issues
Project-URL: Repository, https://github.com/zlai-llm/zlai
